LICENSE
MANIFEST.in
README.md
requirements.txt
setup.py
q3rcon/__init__.py
q3rcon/q3rcon_cli.py
q3rcon/q3rcon_web.py
q3rcon/rcon.py
q3rcon.egg-info/PKG-INFO
q3rcon.egg-info/SOURCES.txt
q3rcon.egg-info/dependency_links.txt
q3rcon.egg-info/entry_points.txt
q3rcon.egg-info/top_level.txt
q3rcon/data/.DS_Store
q3rcon/data/static/.DS_Store
q3rcon/data/static/javascript.js
q3rcon/data/static/style.css
q3rcon/data/static/images/q3ctf1.jpg
q3rcon/data/static/images/q3ctf2.jpg
q3rcon/data/static/images/q3ctf3.jpg
q3rcon/data/static/images/q3ctf4.jpg
q3rcon/data/static/images/q3dm1.jpg
q3rcon/data/static/images/q3dm10.jpg
q3rcon/data/static/images/q3dm11.jpg
q3rcon/data/static/images/q3dm12.jpg
q3rcon/data/static/images/q3dm13.jpg
q3rcon/data/static/images/q3dm14.jpg
q3rcon/data/static/images/q3dm15.jpg
q3rcon/data/static/images/q3dm16.jpg
q3rcon/data/static/images/q3dm17.jpg
q3rcon/data/static/images/q3dm18.jpg
q3rcon/data/static/images/q3dm19.jpg
q3rcon/data/static/images/q3dm2.jpg
q3rcon/data/static/images/q3dm3.jpg
q3rcon/data/static/images/q3dm4.jpg
q3rcon/data/static/images/q3dm5.jpg
q3rcon/data/static/images/q3dm6.jpg
q3rcon/data/static/images/q3dm7.jpg
q3rcon/data/static/images/q3dm8.jpg
q3rcon/data/static/images/q3dm9.jpg
q3rcon/data/static/images/q3tourney1.jpg
q3rcon/data/static/images/q3tourney2.jpg
q3rcon/data/static/images/q3tourney3.jpg
q3rcon/data/static/images/q3tourney4.jpg
q3rcon/data/static/images/q3tourney5.jpg
q3rcon/data/static/images/q3tourney6.jpg
q3rcon/data/templates/map.html
q3rcon/data/templates/page.html