Metadata-Version: 2.1
Name: q3rcon
Version: 0.1
Summary: Quake 3 remote console
Home-page: https://github.com/acoomans/q3rcon
Author: Arnaud Coomans
Author-email: hello@acoomans.com
License: BSD
Platform: any
License-File: LICENSE
